[
    {
        "author": "Pete Hunt",
        "text": "Hey there!"
    },
    {
        "author": "Paul O",
        "text": "React is *great*!"
    },
    {
        "author": "Jard",
        "text": "hi hihihsdf s d"
    },
    {
        "author": "jojo",
        "text": "jojojojoj hihdpv aidsv piu"
    },
    {
        "author": "harry",
        "text": "eat a burger"
    },
    {
        "author": "hat",
        "text": "hathathat"
    },
    {
        "author": "ace",
        "text": "face hat"
    },
    {
        "author": "face",
        "text": "fahaosdjvpj idjnvp wijdvnp qwijvdn"
    },
    {
        "author": "catdob",
        "text": "dlkj po sdpv  pin dvpi v"
    }
]